<b:beans xmlns="http://www.springframework.org/schema/security"
         xmlns:b="http://www.springframework.org/schema/beans"
         xmlns:xsi="http://www.w3.org/2001/XMLSchema-instance"
         xsi:schemaLocation="http://www.springframework.org/schema/beans http://www.springframework.org/schema/beans/spring-beans.xsd
						http://www.springframework.org/schema/security http://www.springframework.org/schema/security/spring-security.xsd">

    <http auto-config="true">
        <http-basic />
        <intercept-url pattern="/v1" access="permitAll" />
        <intercept-url pattern="/v1/templates" access="hasRole('ROLE_USER')" />
        <intercept-url pattern="/v1/subscriptions" access="hasRole('ROLE_USER')" />
        <intercept-url pattern="/v1/publications" access="hasRole('ROLE_USER')" />
        <intercept-url pattern="/v1/deliveryMethods" access="hasRole('ROLE_USER')" />
        <intercept-url pattern="/v1/events" access="hasRole('ROLE_USER')" />
    </http>

    <authentication-manager>
        <authentication-provider>
            <user-service>
                <user name="dummy-user" password="asdf" authorities="ROLE_USER" />
                <user name="dummy-user2" password="asdf" authorities="ROLE_USER" />
                <user name="not-in-dao" password="asdf" authorities="ROLE_USER" />
            </user-service>
        </authentication-provider>
    </authentication-manager>

</b:beans>
